BeginnersbookJstlJiaochengChuyi/README.md
BeginnersbookJstlJiaochengChuyi/__init__.py
BeginnersbookJstlJiaochengChuyi/__main__.py
BeginnersbookJstlJiaochengChuyi/file.epub
BeginnersbookJstlJiaochengChuyi/index.html
BeginnersbookJstlJiaochengChuyi/css/__init__.py
BeginnersbookJstlJiaochengChuyi/css/annotations.css
BeginnersbookJstlJiaochengChuyi/css/main.css
BeginnersbookJstlJiaochengChuyi/css/normalize.css
BeginnersbookJstlJiaochengChuyi/css/popup.css
BeginnersbookJstlJiaochengChuyi/font/__init__.py
BeginnersbookJstlJiaochengChuyi/font/fontello.eot
BeginnersbookJstlJiaochengChuyi/font/fontello.svg
BeginnersbookJstlJiaochengChuyi/font/fontello.ttf
BeginnersbookJstlJiaochengChuyi/font/fontello.woff
BeginnersbookJstlJiaochengChuyi/img/__init__.py
BeginnersbookJstlJiaochengChuyi/img/annotator-glyph-sprite.png
BeginnersbookJstlJiaochengChuyi/img/annotator-icon-sprite.png
BeginnersbookJstlJiaochengChuyi/img/apple-touch-icon.png
BeginnersbookJstlJiaochengChuyi/img/cancelfullscreen.png
BeginnersbookJstlJiaochengChuyi/img/close.png
BeginnersbookJstlJiaochengChuyi/img/fullscreen.png
BeginnersbookJstlJiaochengChuyi/img/loader.gif
BeginnersbookJstlJiaochengChuyi/img/menu-icon.png
BeginnersbookJstlJiaochengChuyi/img/save.png
BeginnersbookJstlJiaochengChuyi/img/saved.png
BeginnersbookJstlJiaochengChuyi/img/settings-s.png
BeginnersbookJstlJiaochengChuyi/img/settings.png
BeginnersbookJstlJiaochengChuyi/img/star.png
BeginnersbookJstlJiaochengChuyi/js/__init__.py
BeginnersbookJstlJiaochengChuyi/js/epub.js
BeginnersbookJstlJiaochengChuyi/js/epub.min.js
BeginnersbookJstlJiaochengChuyi/js/epub.min.map
BeginnersbookJstlJiaochengChuyi/js/hooks.min.js
BeginnersbookJstlJiaochengChuyi/js/hooks.min.map
BeginnersbookJstlJiaochengChuyi/js/reader.js
BeginnersbookJstlJiaochengChuyi/js/reader.js.map
BeginnersbookJstlJiaochengChuyi/js/reader.min.js
BeginnersbookJstlJiaochengChuyi/js/reader.min.map
BeginnersbookJstlJiaochengChuyi/js/hooks/__init__.py
beginnersbook_jstl_jiaocheng_chuyi-2024.3.5.0.dist-info/METADATA
beginnersbook_jstl_jiaocheng_chuyi-2024.3.5.0.dist-info/WHEEL
beginnersbook_jstl_jiaocheng_chuyi-2024.3.5.0.dist-info/entry_points.txt
beginnersbook_jstl_jiaocheng_chuyi-2024.3.5.0.dist-info/top_level.txt
beginnersbook_jstl_jiaocheng_chuyi-2024.3.5.0.dist-info/RECORD
